envutils/__init__.py
envutils/envutils.py
envutils/version.py
envutils/tests/__init__.py
envutils/tests/test_envutils.py
envutils-1.0.0.dist-info/LICENSE.txt
envutils-1.0.0.dist-info/METADATA
envutils-1.0.0.dist-info/WHEEL
envutils-1.0.0.dist-info/top_level.txt
envutils-1.0.0.dist-info/RECORD
