Metadata-Version: 2.1
Name: envutils
Version: 1.0.0
Summary: A python library to read and parse environment variables
Home-page: https://github.com/mfilippo/envutils
Author: Matteo Filipponi
Author-email: matteofilipponi@hotmail.com
License: UNKNOWN
Platform: UNKNOWN
Classifier: Programming Language :: Python :: 3
Classifier: License :: OSI Approved :: MIT License
Classifier: Operating System :: OS Independent
